cv_parsing/__init__.py
cv_parsing/data/Dataloader.py
cv_parsing/data/__init__.py
cv_parsing/exceptions/EvaluationException.py
cv_parsing/exceptions/JSONException.py
cv_parsing/exceptions/ORMException.py
cv_parsing/exceptions/PromptException.py
cv_parsing/exceptions/__init__.py
cv_parsing/main/Evaluation.py
cv_parsing/main/ManualAnnotation.py
cv_parsing/main/Predict.py
cv_parsing/main/__init__.py
cv_parsing/orms/Education.py
cv_parsing/orms/Job.py
cv_parsing/orms/Language.py
cv_parsing/orms/LanguageLevel.py
cv_parsing/orms/ORM.py
cv_parsing/orms/Person.py
cv_parsing/orms/PersonalInformation.py
cv_parsing/orms/__init__.py
cv_parsing/parser/Parser.py
cv_parsing/parser/ParsingStrategy.py
cv_parsing/parser/__init__.py
cv_parsing/parser/strategies/HuggingFaceApiStrategy.py
cv_parsing/parser/strategies/OllamaStrategy.py
cv_parsing/parser/strategies/OpenAIStrategy.py
cv_parsing/parser/strategies/__init__.py
cv_parsing/prompts/EnglishPrompt.py
cv_parsing/prompts/PortuguesePrompt.py
cv_parsing/prompts/Prompt.py
cv_parsing/prompts/__init__.py
cv_parsing/utils/__init__.py
cv_parsing/utils/clean_text.py
cv_parsing/utils/json_utils.py
cv_parsing/utils/logger.py
cv_parsing/utils/metrics.py
cv_parsing/utils/schema.jsonl
cv_parsing/utils/utils.py
cv_parsing-0.3.0.dist-info/METADATA
cv_parsing-0.3.0.dist-info/WHEEL
cv_parsing-0.3.0.dist-info/top_level.txt
cv_parsing-0.3.0.dist-info/RECORD
